pyucalgarysrs/__init__.py
pyucalgarysrs/_util.py
pyucalgarysrs/data/__init__.py
pyucalgarysrs/data/_download.py
pyucalgarysrs/data/_list.py
pyucalgarysrs/data/classes.py
pyucalgarysrs/data/read/__init__.py
pyucalgarysrs/data/read/_calibration.py
pyucalgarysrs/data/read/_grid.py
pyucalgarysrs/data/read/_norstar_riometer.py
pyucalgarysrs/data/read/_rego.py
pyucalgarysrs/data/read/_skymap.py
pyucalgarysrs/data/read/_smile.py
pyucalgarysrs/data/read/_swan_hsr.py
pyucalgarysrs/data/read/_themis.py
pyucalgarysrs/data/read/_trex_blue.py
pyucalgarysrs/data/read/_trex_nir.py
pyucalgarysrs/data/read/_trex_rgb.py
pyucalgarysrs/data/read/_trex_spectrograph.py
pyucalgarysrs/exceptions.py
pyucalgarysrs/models/__init__.py
pyucalgarysrs/models/atm/__init__.py
pyucalgarysrs/models/atm/_forward.py
pyucalgarysrs/models/atm/_inverse.py
pyucalgarysrs/models/atm/classes_forward.py
pyucalgarysrs/models/atm/classes_inverse.py
pyucalgarysrs/pyucalgarysrs.py
pyucalgarysrs-1.26.1.dist-info/METADATA
pyucalgarysrs-1.26.1.dist-info/WHEEL
pyucalgarysrs-1.26.1.dist-info/licenses/LICENSE
pyucalgarysrs-1.26.1.dist-info/RECORD
