Metadata-Version: 2.4
Name: pyucalgarysrs
Version: 1.26.1
Summary: Tools for interacting with UCalgary Space Remote Sensing data
License: Apache-2.0
License-File: LICENSE
Author: Darren Chaddock
Author-email: dchaddoc@ucalgary.ca
Maintainer: Darren Chaddock
Maintainer-email: dchaddoc@ucalgary.ca
Requires-Python: >=3.10
Classifier: License :: OSI Approved :: Apache Software License
Classifier: Programming Language :: Python :: 3
Classifier: Programming Language :: Python :: 3.10
Classifier: Programming Language :: Python :: 3.11
Classifier: Programming Language :: Python :: 3.12
Classifier: Programming Language :: Python :: 3.13
Classifier: Programming Language :: Python :: 3.14
Requires-Dist: h5py (>=3.1.0,<4.0.0)
Requires-Dist: humanize (>=4.4.0,<5.0.0)
Requires-Dist: numpy (>=1.21.0,<2.3.0) ; python_version == "3.10"
Requires-Dist: numpy (>=1.21.0,<3.0.0) ; python_version >= "3.11"
Requires-Dist: opencv-python (>=4.4.0,<5.0.0)
Requires-Dist: requests (>=2.28.0,<3.0.0)
Requires-Dist: scipy (>=1.9.0,<2.0.0)
Requires-Dist: texttable (>=1.6.4,<2.0.0)
Requires-Dist: tqdm (>=4.61.2,<5.0.0)
Project-URL: API Reference, https://docs-pyucalgarysrs.phys.ucalgary.ca/
Project-URL: Homepage, https://github.com/ucalgary-srs/pyUCalgarySRS
Project-URL: Repository, https://github.com/ucalgary-srs/pyUCalgarySRS
Project-URL: UCalgary SRS Open Data Platform, https://data.phys.ucalgary.ca
